hdl/mult_by_constant.vhd
--------------------------------------------------------------------------------
--
-- Title    : mult_by_constant.vhd
-- Project  : PDS 2020
-- Author   : GOnzalo Lavigna
-- Date     : 02/JUL/2020
--------------------------------------------------------------------------------
--
-- Description
-- Multiplicar poru nas constante un stream proveniente de AXI y devolverlo en AXIS.
-- Depende del usuario utilizar como corresponde el corrimiento y la utilización de la 
-- coma.
--------------------------------------------------------------------------------

library ieee ;
    use ieee.std_logic_1164.all ;
    use ieee.numeric_std.all ;

entity mult_by_constant is
  generic (
          DATA_IN_WIDTH     : integer := 16;
          DATA_OUT_WIDTH    : integer := 32;
          CONST_VALUE       : integer := 1
      );

  port (
        clk_i             : IN std_logic;
        reset_ni          : IN std_logic;
        data_i            : IN  std_logic_vector(DATA_IN_WIDTH-1 downto 0);
        data_o            : OUT std_logic_vector(DATA_OUT_WIDTH-1 downto 0)
    );
end entity ; -- mult_by_constant

architecture rtl of mult_by_constant is

signal temp : integer;

begin

temp <= to_integer(signed(data_i));

data_o <= std_logic_vector(to_signed(CONST_VALUE *temp,32));

end architecture ; -- rtl

wave.vcd
$date
  Mon Oct 24 19:52:49 2022
$end
$version
  GHDL v0
$end
$timescale
  1 fs
$end
$scope module standard $end
$upscope $end
$scope module std_logic_1164 $end
$upscope $end
$scope module numeric_std $end
$upscope $end
$scope module mult_by_constant $end
$var reg 1 ! clk_i $end
$var reg 1 " reset_ni $end
$var reg 16 # data_i[15:0] $end
$var reg 32 $ data_o[31:0] $end
$var integer 32 % temp $end
$upscope $end
$enddefinitions $end
#0
U!
0"
bUUUUUUUUUUUUUUUU #
b00000000000000000000000000000000 $
b0 %
#1000000000
1"
#2000000000
#3000000000
0!
b0000010000000100 #
b00000000000000000000010000000100 $
b10000000100 %
#3001000000
1!
#3002000000
0!
b0000100000000101 #
b00000000000000000000100000000101 $
b100000000101 %
#3003000000
1!
#3004000000
0!
b0000101111111110 #
b00000000000000000000101111111110 $
b101111111110 %
#3005000000
1!
#3006000000
0!
b0000111111101010 #
b00000000000000000000111111101010 $
b111111101010 %
#3007000000
1!
#3008000000
0!
b0001001111000110 #
b00000000000000000001001111000110 $
b1001111000110 %
#3009000000
1!
#3010000000
0!
b0001011110001111 #
b00000000000000000001011110001111 $
b1011110001111 %
#3011000000
1!
#3012000000
0!
b0001101100111111 #
b00000000000000000001101100111111 $
b1101100111111 %
#3013000000
1!
#3014000000
0!
b0001111011010101 #
b00000000000000000001111011010101 $
b1111011010101 %
#3015000000
1!
#3016000000
0!
b0010001001001010 #
b00000000000000000010001001001010 $
b10001001001010 %
#3017000000
1!
#3018000000
0!
b0010010110011110 #
b00000000000000000010010110011110 $
b10010110011110 %
#3019000000
1!
#3020000000
0!
b0010100011001011 #
b00000000000000000010100011001011 $
b10100011001011 %
#3021000000
1!
#3022000000
0!
b0010101111001111 #
b00000000000000000010101111001111 $
b10101111001111 %
#3023000000
1!
#3024000000
0!
b0010111010100111 #
b00000000000000000010111010100111 $
b10111010100111 %
#3025000000
1!
#3026000000
0!
b0011000101010000 #
b00000000000000000011000101010000 $
b11000101010000 %
#3027000000
1!
#3028000000
0!
b0011001111000110 #
b00000000000000000011001111000110 $
b11001111000110 %
#3029000000
1!
#3030000000
0!
b0011011000001001 #
b00000000000000000011011000001001 $
b11011000001001 %
#3031000000
1!
#3032000000
0!
b0011100000010101 #
b00000000000000000011100000010101 $
b11100000010101 %
#3033000000
1!
#3034000000
0!
b0011100111101000 #
b00000000000000000011100111101000 $
b11100111101000 %
#3035000000
1!
#3036000000
0!
b0011101110000001 #
b00000000000000000011101110000001 $
b11101110000001 %
#3037000000
1!
#3038000000
0!
b0011110011011110 #
b00000000000000000011110011011110 $
b11110011011110 %
#3039000000
1!
#3040000000
0!
b0011110111111101 #
b00000000000000000011110111111101 $
b11110111111101 %
#3041000000
1!
#3042000000
0!
b0011111011011101 #
b00000000000000000011111011011101 $
b11111011011101 %
#3043000000
1!
#3044000000
0!
b0011111101111110 #
b00000000000000000011111101111110 $
b11111101111110 %
#3045000000
1!
#3046000000
0!
b0011111111011111 #
b00000000000000000011111111011111 $
b11111111011111 %
#3047000000
1!
#3048000000
0!
b0011111111111111 #
b00000000000000000011111111111111 $
b11111111111111 %
#3049000000
1!
#3050000000
0!
b0011111111011111 #
b00000000000000000011111111011111 $
b11111111011111 %
#3051000000
1!
#3052000000
0!
b0011111101111110 #
b00000000000000000011111101111110 $
b11111101111110 %
#3053000000
1!
#3054000000
0!
b0011111011011101 #
b00000000000000000011111011011101 $
b11111011011101 %
#3055000000
1!
#3056000000
0!
b0011110111111101 #
b00000000000000000011110111111101 $
b11110111111101 %
#3057000000
1!
#3058000000
0!
b0011110011011110 #
b00000000000000000011110011011110 $
b11110011011110 %
#3059000000
1!
#3060000000
0!
b0011101110000001 #
b00000000000000000011101110000001 $
b11101110000001 %
#3061000000
1!
#3062000000
0!
b0011100111101000 #
b00000000000000000011100111101000 $
b11100111101000 %
#3063000000
1!
#3064000000
0!
b0011100000010101 #
b00000000000000000011100000010101 $
b11100000010101 %
#3065000000
1!
#3066000000
0!
b0011011000001001 #
b00000000000000000011011000001001 $
b11011000001001 %
#3067000000
1!
#3068000000
0!
b0011001111000110 #
b00000000000000000011001111000110 $
b11001111000110 %
#3069000000
1!
#3070000000
0!
b0011000101010000 #
b00000000000000000011000101010000 $
b11000101010000 %
#3071000000
1!
#3072000000
0!
b0010111010100111 #
b00000000000000000010111010100111 $
b10111010100111 %
#3073000000
1!
#3074000000
0!
b0010101111001111 #
b00000000000000000010101111001111 $
b10101111001111 %
#3075000000
1!
#3076000000
0!
b0010100011001011 #
b00000000000000000010100011001011 $
b10100011001011 %
#3077000000
1!
#3078000000
0!
b0010010110011110 #
b00000000000000000010010110011110 $
b10010110011110 %
#3079000000
1!
#3080000000
0!
b0010001001001010 #
b00000000000000000010001001001010 $
b10001001001010 %
#3081000000
1!
#3082000000
0!
b0001111011010101 #
b00000000000000000001111011010101 $
b1111011010101 %
#3083000000
1!
#3084000000
0!
b0001101100111111 #
b00000000000000000001101100111111 $
b1101100111111 %
#3085000000
1!
#3086000000
0!
b0001011110001111 #
b00000000000000000001011110001111 $
b1011110001111 %
#3087000000
1!
#3088000000
0!
b0001001111000110 #
b00000000000000000001001111000110 $
b1001111000110 %
#3089000000
1!
#3090000000
0!
b0000111111101010 #
b00000000000000000000111111101010 $
b111111101010 %
#3091000000
1!
#3092000000
0!
b0000101111111110 #
b00000000000000000000101111111110 $
b101111111110 %
#3093000000
1!
#3094000000
0!
b0000100000000101 #
b00000000000000000000100000000101 $
b100000000101 %
#3095000000
1!
#3096000000
0!
b0000010000000100 #
b00000000000000000000010000000100 $
b10000000100 %
#3097000000
1!
#3098000000
0!
b0000000000000000 #
b00000000000000000000000000000000 $
b0 %
#3099000000
1!
#3100000000
0!
b1111101111111100 #
b11111111111111111111101111111100 $
b11111111111111111111101111111100 %
#3101000000
1!
#3102000000
0!
b1111011111111011 #
b11111111111111111111011111111011 $
b11111111111111111111011111111011 %
#3103000000
1!
#3104000000
0!
b1111010000000010 #
b11111111111111111111010000000010 $
b11111111111111111111010000000010 %
#3105000000
1!
#3106000000
0!
b1111000000010110 #
b11111111111111111111000000010110 $
b11111111111111111111000000010110 %
#3107000000
1!
#3108000000
0!
b1110110000111010 #
b11111111111111111110110000111010 $
b11111111111111111110110000111010 %
#3109000000
1!
#3110000000
0!
b1110100001110001 #
b11111111111111111110100001110001 $
b11111111111111111110100001110001 %
#3111000000
1!
#3112000000
0!
b1110010011000001 #
b11111111111111111110010011000001 $
b11111111111111111110010011000001 %
#3113000000
1!
#3114000000
0!
b1110000100101011 #
b11111111111111111110000100101011 $
b11111111111111111110000100101011 %
#3115000000
1!
#3116000000
0!
b1101110110110110 #
b11111111111111111101110110110110 $
b11111111111111111101110110110110 %
#3117000000
1!
#3118000000
0!
b1101101001100010 #
b11111111111111111101101001100010 $
b11111111111111111101101001100010 %
#3119000000
1!
#3120000000
0!
b1101011100110101 #
b11111111111111111101011100110101 $
b11111111111111111101011100110101 %
#3121000000
1!
#3122000000
0!
b1101010000110001 #
b11111111111111111101010000110001 $
b11111111111111111101010000110001 %
#3123000000
1!
#3124000000
0!
b1101000101011001 #
b11111111111111111101000101011001 $
b11111111111111111101000101011001 %
#3125000000
1!
#3126000000
0!
b1100111010110000 #
b11111111111111111100111010110000 $
b11111111111111111100111010110000 %
#3127000000
1!
#3128000000
0!
b1100110000111010 #
b11111111111111111100110000111010 $
b11111111111111111100110000111010 %
#3129000000
1!
#3130000000
0!
b1100100111110111 #
b11111111111111111100100111110111 $
b11111111111111111100100111110111 %
#3131000000
1!
#3132000000
0!
b1100011111101011 #
b11111111111111111100011111101011 $
b11111111111111111100011111101011 %
#3133000000
1!
#3134000000
0!
b1100011000011000 #
b11111111111111111100011000011000 $
b11111111111111111100011000011000 %
#3135000000
1!
#3136000000
0!
b1100010001111111 #
b11111111111111111100010001111111 $
b11111111111111111100010001111111 %
#3137000000
1!
#3138000000
0!
b1100001100100010 #
b11111111111111111100001100100010 $
b11111111111111111100001100100010 %
#3139000000
1!
#3140000000
0!
b1100001000000011 #
b11111111111111111100001000000011 $
b11111111111111111100001000000011 %
#3141000000
1!
#3142000000
0!
b1100000100100011 #
b11111111111111111100000100100011 $
b11111111111111111100000100100011 %
#3143000000
1!
#3144000000
0!
b1100000010000010 #
b11111111111111111100000010000010 $
b11111111111111111100000010000010 %
#3145000000
1!
#3146000000
0!
b1100000000100001 #
b11111111111111111100000000100001 $
b11111111111111111100000000100001 %
#3147000000
1!
#3148000000
0!
b1100000000000000 #
b11111111111111111100000000000000 $
b11111111111111111100000000000000 %
#3149000000
1!
#3150000000
0!
b1100000000100001 #
b11111111111111111100000000100001 $
b11111111111111111100000000100001 %
#3151000000
1!
#3152000000
0!
b1100000010000010 #
b11111111111111111100000010000010 $
b11111111111111111100000010000010 %
#3153000000
1!
#3154000000
0!
b1100000100100011 #
b11111111111111111100000100100011 $
b11111111111111111100000100100011 %
#3155000000
1!
#3156000000
0!
b1100001000000011 #
b11111111111111111100001000000011 $
b11111111111111111100001000000011 %
#3157000000
1!
#3158000000
0!
b1100001100100010 #
b11111111111111111100001100100010 $
b11111111111111111100001100100010 %
#3159000000
1!
#3160000000
0!
b1100010001111111 #
b11111111111111111100010001111111 $
b11111111111111111100010001111111 %
#3161000000
1!
#3162000000
0!
b1100011000011000 #
b11111111111111111100011000011000 $
b11111111111111111100011000011000 %
#3163000000
1!
#3164000000
0!
b1100011111101011 #
b11111111111111111100011111101011 $
b11111111111111111100011111101011 %
#3165000000
1!
#3166000000
0!
b1100100111110111 #
b11111111111111111100100111110111 $
b11111111111111111100100111110111 %
#3167000000
1!
#3168000000
0!
b1100110000111010 #
b11111111111111111100110000111010 $
b11111111111111111100110000111010 %
#3169000000
1!
#3170000000
0!
b1100111010110000 #
b11111111111111111100111010110000 $
b11111111111111111100111010110000 %
#3171000000
1!
#3172000000
0!
b1101000101011001 #
b11111111111111111101000101011001 $
b11111111111111111101000101011001 %
#3173000000
1!
#3174000000
0!
b1101010000110001 #
b11111111111111111101010000110001 $
b11111111111111111101010000110001 %
#3175000000
1!
#3176000000
0!
b1101011100110101 #
b11111111111111111101011100110101 $
b11111111111111111101011100110101 %
#3177000000
1!
#3178000000
0!
b1101101001100010 #
b11111111111111111101101001100010 $
b11111111111111111101101001100010 %
#3179000000
1!
#3180000000
0!
b1101110110110110 #
b11111111111111111101110110110110 $
b11111111111111111101110110110110 %
#3181000000
1!
#3182000000
0!
b1110000100101011 #
b11111111111111111110000100101011 $
b11111111111111111110000100101011 %
#3183000000
1!
#3184000000
0!
b1110010011000001 #
b11111111111111111110010011000001 $
b11111111111111111110010011000001 %
#3185000000
1!
#3186000000
0!
b1110100001110001 #
b11111111111111111110100001110001 $
b11111111111111111110100001110001 %
#3187000000
1!
#3188000000
0!
b1110110000111010 #
b11111111111111111110110000111010 $
b11111111111111111110110000111010 %
#3189000000
1!
#3190000000
0!
b1111000000010110 #
b11111111111111111111000000010110 $
b11111111111111111111000000010110 %
#3191000000
1!
#3192000000
0!
b1111010000000010 #
b11111111111111111111010000000010 $
b11111111111111111111010000000010 %
#3193000000
1!
#3194000000
0!
b1111011111111011 #
b11111111111111111111011111111011 $
b11111111111111111111011111111011 %
#3195000000
1!
#3196000000
0!
b1111101111111100 #
b11111111111111111111101111111100 $
b11111111111111111111101111111100 %
#3197000000
1!
#3198000000
0!
b0000000000000000 #
b00000000000000000000000000000000 $
b0 %
